{
  "objective": "maximize net profit over 10 yearly windows with strict no-blowup constraint",
  "blowup_definition": "equity <= 0 OR free_margin <= 0",
  "generated_at_utc": "2026-02-26T10:28:28.225008+00:00",
  "data_file": "download/usdchf-m5-bid-2016-02-29-2026-02-26-merged.csv",
  "trials": 0,
  "seed": 1,
  "best_params": {
    "lot": 0.008,
    "k_lot": 1.08,
    "max_lot": 0.8
  },
  "best_aggregate": {
    "sum_net_profit": 8184.649570113448,
    "avg_net_profit": 818.4649570113448,
    "min_year_net_profit": 365.363401187622,
    "blowup_years": 0.0,
    "years_ran": 10.0,
    "worst_year_max_drawdown_pct": 26.83318200275884,
    "min_free_margin": 6165.542623889779,
    "feasible_no_blowup_10y": 1.0
  },
  "yearly_results": [
    {
      "year_idx": 1,
      "start_utc": "2016-02-29T00:00:00+00:00",
      "end_utc": "2017-02-27T23:55:00+00:00",
      "bars": 105120,
      "net_profit": 1400.604858197461,
      "final_balance": 11400.604858197461,
      "max_drawdown_pct": 11.17892060521137,
      "min_free_margin": 8621.118878811234,
      "blew_up": false,
      "blowup_time_utc": "-"
    },
    {
      "year_idx": 2,
      "start_utc": "2017-03-01T00:00:00+00:00",
      "end_utc": "2018-02-27T23:55:00+00:00",
      "bars": 104832,
      "net_profit": 569.157345382484,
      "final_balance": 10569.157345382484,
      "max_drawdown_pct": 12.660536649101124,
      "min_free_margin": 7794.836552013952,
      "blew_up": false,
      "blowup_time_utc": "-"
    },
    {
      "year_idx": 3,
      "start_utc": "2018-02-28T00:00:00+00:00",
      "end_utc": "2019-02-27T23:55:00+00:00",
      "bars": 104832,
      "net_profit": 404.0394862328212,
      "final_balance": 10404.039486232821,
      "max_drawdown_pct": 10.20549266597268,
      "min_free_margin": 8138.750152985804,
      "blew_up": false,
      "blowup_time_utc": "-"
    },
    {
      "year_idx": 4,
      "start_utc": "2019-02-28T00:00:00+00:00",
      "end_utc": "2020-02-27T23:55:00+00:00",
      "bars": 104832,
      "net_profit": 706.7198249761823,
      "final_balance": 10706.719824976182,
      "max_drawdown_pct": 5.497271360867046,
      "min_free_margin": 9107.926571651791,
      "blew_up": false,
      "blowup_time_utc": "-"
    },
    {
      "year_idx": 5,
      "start_utc": "2020-02-28T00:00:00+00:00",
      "end_utc": "2021-02-26T23:55:00+00:00",
      "bars": 104832,
      "net_profit": 1274.7116251630632,
      "final_balance": 11274.711625163063,
      "max_drawdown_pct": 7.439256151793136,
      "min_free_margin": 8704.069803236765,
      "blew_up": false,
      "blowup_time_utc": "-"
    },
    {
      "year_idx": 6,
      "start_utc": "2021-02-27T00:00:00+00:00",
      "end_utc": "2022-02-26T23:55:00+00:00",
      "bars": 104832,
      "net_profit": 755.0127687523036,
      "final_balance": 10755.012768752304,
      "max_drawdown_pct": 7.057211140676242,
      "min_free_margin": 8897.510383324061,
      "blew_up": false,
      "blowup_time_utc": "-"
    },
    {
      "year_idx": 7,
      "start_utc": "2022-02-27T00:00:00+00:00",
      "end_utc": "2023-02-26T23:55:00+00:00",
      "bars": 104832,
      "net_profit": 1003.7205310277132,
      "final_balance": 11003.720531027713,
      "max_drawdown_pct": 26.83318200275884,
      "min_free_margin": 6165.542623889779,
      "blew_up": false,
      "blowup_time_utc": "-"
    },
    {
      "year_idx": 8,
      "start_utc": "2023-02-27T00:00:00+00:00",
      "end_utc": "2024-02-26T23:55:00+00:00",
      "bars": 104832,
      "net_profit": 472.2023163299964,
      "final_balance": 10472.202316329996,
      "max_drawdown_pct": 24.83396297979559,
      "min_free_margin": 6638.383293433168,
      "blew_up": false,
      "blowup_time_utc": "-"
    },
    {
      "year_idx": 9,
      "start_utc": "2024-02-27T00:00:00+00:00",
      "end_utc": "2025-02-25T23:55:00+00:00",
      "bars": 104832,
      "net_profit": 365.363401187622,
      "final_balance": 10365.363401187622,
      "max_drawdown_pct": 16.702115754336187,
      "min_free_margin": 7068.584437348085,
      "blew_up": false,
      "blowup_time_utc": "-"
    },
    {
      "year_idx": 10,
      "start_utc": "2025-02-26T00:00:00+00:00",
      "end_utc": "2026-02-25T23:55:00+00:00",
      "bars": 104832,
      "net_profit": 1233.1174128638013,
      "final_balance": 11233.117412863801,
      "max_drawdown_pct": 25.038179485363337,
      "min_free_margin": 6224.721090192521,
      "blew_up": false,
      "blowup_time_utc": "-"
    }
  ]
}